CHANGES.rst
LICENSE.txt
MANIFEST.in
README.rst
pydgutils_bootstrap.py
requirements.txt
setup.cfg
setup.py
pydgutils/__init__.py
pydgutils/version.py
pydgutils.egg-info/PKG-INFO
pydgutils.egg-info/SOURCES.txt
pydgutils.egg-info/dependency_links.txt
pydgutils.egg-info/top_level.txt
tests/__init__.py
tests/test_pydgutils.py