Metadata-Version: 1.1
Name: pydgutils
Version: 0.0.15
Summary: A library use for downgrade sources to python2 syntax during setup
Home-page: https://github.com/starofrainnight/pydgutils
Author: Hong-She Liang
Author-email: starofrainnight@gmail.com
License: UNKNOWN
Platform: UNKNOWN
Classifier: Development Status :: 3 - Alpha
Classifier: Intended Audience :: Developers
Classifier: License :: OSI Approved :: MIT License
Classifier: Operating System :: OS Independent
Classifier: Programming Language :: Python :: 2
Classifier: Programming Language :: Python :: 3
Classifier: Programming Language :: Python :: Implementation :: CPython
Classifier: Topic :: Software Development :: Libraries
